{
  "Trivia": {
    "num_cities": 364,
    "num_clicks": 62161,
    "num_clicks_per_city": 170.77197802197801,
    "most_played_city": "Mojave, Nat\u2019l Preserve, United States",
    "most_played_city_num_clicks": 287
  },
  "Oceania": {
    "num_cities": 332,
    "num_clicks": 34788,
    "num_clicks_per_city": 104.78313253012048,
    "most_played_city": "Funafuti, Tuvalu",
    "most_played_city_num_clicks": 404
  },
  "NAmerica": {
    "num_cities": 635,
    "num_clicks": 64491,
    "num_clicks_per_city": 101.56062992125985,
    "most_played_city": "Edmonton, Alberta, Canada",
    "most_played_city_num_clicks": 347
  },
  "Europe": {
    "num_cities": 582,
    "num_clicks": 122161,
    "num_clicks_per_city": 209.89862542955328,
    "most_played_city": "Ko\u0161ice, Slovakia",
    "most_played_city_num_clicks": 374
  },
  "SAmerica": {
    "num_cities": 520,
    "num_clicks": 24603,
    "num_clicks_per_city": 47.31346153846154,
    "most_played_city": "Basseterre, Saint Kitts And Nevis",
    "most_played_city_num_clicks": 238
  },
  "Asia": {
    "num_cities": 596,
    "num_clicks": 44282,
    "num_clicks_per_city": 74.29865771812081,
    "most_played_city": "Male, Maldives",
    "most_played_city_num_clicks": 180
  },
  "World": {
    "num_cities": 1012,
    "num_clicks": 224888,
    "num_clicks_per_city": 222.22134387351778,
    "most_played_city": "Monaco, Monaco",
    "most_played_city_num_clicks": 368
  },
  "Africa": {
    "num_cities": 446,
    "num_clicks": 37530,
    "num_clicks_per_city": 84.14798206278027,
    "most_played_city": "Djougou, Benin",
    "most_played_city_num_clicks": 142
  },
  "Total": {
    "num_clicks": 614904
  }
}