{
  "Trivia": {
    "num_cities": 379,
    "num_clicks": 93312,
    "num_clicks_per_city": 246.20580474934036,
    "most_played_city": "Zion, Nat\u2019l Park, United States",
    "most_played_city_num_clicks": 416
  },
  "Oceania": {
    "num_cities": 332,
    "num_clicks": 54487,
    "num_clicks_per_city": 164.11746987951807,
    "most_played_city": "Palikir, Micronesia, Federated States Of",
    "most_played_city_num_clicks": 682
  },
  "NAmerica": {
    "num_cities": 635,
    "num_clicks": 106271,
    "num_clicks_per_city": 167.35590551181102,
    "most_played_city": "San Pedro Sula, Honduras",
    "most_played_city_num_clicks": 447
  },
  "Europe": {
    "num_cities": 582,
    "num_clicks": 168583,
    "num_clicks_per_city": 289.6615120274914,
    "most_played_city": "Brno, Czechia",
    "most_played_city_num_clicks": 503
  },
  "SAmerica": {
    "num_cities": 521,
    "num_clicks": 41827,
    "num_clicks_per_city": 80.28214971209214,
    "most_played_city": "Roseau, Dominica",
    "most_played_city_num_clicks": 343
  },
  "Asia": {
    "num_cities": 596,
    "num_clicks": 74291,
    "num_clicks_per_city": 124.6493288590604,
    "most_played_city": "Male, Maldives",
    "most_played_city_num_clicks": 237
  },
  "World": {
    "num_cities": 1012,
    "num_clicks": 325622,
    "num_clicks_per_city": 321.7608695652174,
    "most_played_city": "Palikir, Micronesia, Federated States Of",
    "most_played_city_num_clicks": 525
  },
  "Africa": {
    "num_cities": 446,
    "num_clicks": 59874,
    "num_clicks_per_city": 134.24663677130044,
    "most_played_city": "Bulawayo, Zimbabwe",
    "most_played_city_num_clicks": 206
  },
  "Total": {
    "num_clicks": 924267
  }
}