{
  "Trivia": {
    "num_cities": 356,
    "num_clicks": 48972,
    "num_clicks_per_city": 137.56179775280899,
    "most_played_city": "Mojave, Nat\u2019l Preserve, United States",
    "most_played_city_num_clicks": 251
  },
  "Oceania": {
    "num_cities": 332,
    "num_clicks": 26015,
    "num_clicks_per_city": 78.35843373493977,
    "most_played_city": "Funafuti, Tuvalu",
    "most_played_city_num_clicks": 318
  },
  "NAmerica": {
    "num_cities": 635,
    "num_clicks": 51692,
    "num_clicks_per_city": 81.40472440944882,
    "most_played_city": "San Pedro Sula, Honduras",
    "most_played_city_num_clicks": 323
  },
  "Europe": {
    "num_cities": 582,
    "num_clicks": 95869,
    "num_clicks_per_city": 164.7233676975945,
    "most_played_city": "Brno, Czechia",
    "most_played_city_num_clicks": 301
  },
  "SAmerica": {
    "num_cities": 513,
    "num_clicks": 19004,
    "num_clicks_per_city": 37.044834307992204,
    "most_played_city": "Roseau, Dominica",
    "most_played_city_num_clicks": 195
  },
  "Asia": {
    "num_cities": 596,
    "num_clicks": 28548,
    "num_clicks_per_city": 47.899328859060404,
    "most_played_city": "Male, Maldives",
    "most_played_city_num_clicks": 157
  },
  "World": {
    "num_cities": 1012,
    "num_clicks": 170233,
    "num_clicks_per_city": 168.21442687747034,
    "most_played_city": "Abu Dhabi, United Arab Emirates",
    "most_played_city_num_clicks": 283
  },
  "Africa": {
    "num_cities": 446,
    "num_clicks": 31556,
    "num_clicks_per_city": 70.75336322869956,
    "most_played_city": "Bulawayo, Zimbabwe",
    "most_played_city_num_clicks": 122
  },
  "Total": {
    "num_clicks": 471889
  }
}