{
  "Trivia": {
    "num_cities": 327,
    "num_clicks": 30841,
    "num_clicks_per_city": 94.31498470948013,
    "most_played_city": "Mojave, Nat\u2019l Preserve, United States",
    "most_played_city_num_clicks": 193
  },
  "Oceania": {
    "num_cities": 332,
    "num_clicks": 13294,
    "num_clicks_per_city": 40.04216867469879,
    "most_played_city": "Funafuti, Tuvalu",
    "most_played_city_num_clicks": 166
  },
  "NAmerica": {
    "num_cities": 635,
    "num_clicks": 30618,
    "num_clicks_per_city": 48.21732283464567,
    "most_played_city": "San Pedro Sula, Honduras",
    "most_played_city_num_clicks": 271
  },
  "Europe": {
    "num_cities": 580,
    "num_clicks": 59107,
    "num_clicks_per_city": 101.90862068965517,
    "most_played_city": "Cork, Ireland",
    "most_played_city_num_clicks": 199
  },
  "SAmerica": {
    "num_cities": 451,
    "num_clicks": 12796,
    "num_clicks_per_city": 28.37250554323725,
    "most_played_city": "Roseau, Dominica",
    "most_played_city_num_clicks": 142
  },
  "Asia": {
    "num_cities": 596,
    "num_clicks": 16405,
    "num_clicks_per_city": 27.5251677852349,
    "most_played_city": "Male, Maldives",
    "most_played_city_num_clicks": 127
  },
  "World": {
    "num_cities": 1010,
    "num_clicks": 116676,
    "num_clicks_per_city": 115.52079207920792,
    "most_played_city": "Maracaibo, Venezuela",
    "most_played_city_num_clicks": 204
  },
  "Africa": {
    "num_cities": 446,
    "num_clicks": 18678,
    "num_clicks_per_city": 41.87892376681614,
    "most_played_city": "Bulawayo, Zimbabwe",
    "most_played_city_num_clicks": 82
  },
  "Total": {
    "num_clicks": 298415
  }
}