{
  "Trivia": {
    "num_cities": 339,
    "num_clicks": 37262,
    "num_clicks_per_city": 109.91740412979351,
    "most_played_city": "Mojave, Nat\u2019l Preserve, United States",
    "most_played_city_num_clicks": 217
  },
  "Oceania": {
    "num_cities": 332,
    "num_clicks": 19209,
    "num_clicks_per_city": 57.85843373493976,
    "most_played_city": "Funafuti, Tuvalu",
    "most_played_city_num_clicks": 231
  },
  "NAmerica": {
    "num_cities": 635,
    "num_clicks": 38885,
    "num_clicks_per_city": 61.23622047244095,
    "most_played_city": "Edmonton, Alberta, Canada",
    "most_played_city_num_clicks": 299
  },
  "Europe": {
    "num_cities": 581,
    "num_clicks": 77656,
    "num_clicks_per_city": 133.6592082616179,
    "most_played_city": "Brno, Czechia",
    "most_played_city_num_clicks": 249
  },
  "SAmerica": {
    "num_cities": 498,
    "num_clicks": 15871,
    "num_clicks_per_city": 31.869477911646587,
    "most_played_city": "Roseau, Dominica",
    "most_played_city_num_clicks": 170
  },
  "Asia": {
    "num_cities": 596,
    "num_clicks": 20110,
    "num_clicks_per_city": 33.741610738255034,
    "most_played_city": "Male, Maldives",
    "most_played_city_num_clicks": 142
  },
  "World": {
    "num_cities": 1011,
    "num_clicks": 141076,
    "num_clicks_per_city": 139.54104846686448,
    "most_played_city": "Cairo, Egypt",
    "most_played_city_num_clicks": 248
  },
  "Africa": {
    "num_cities": 446,
    "num_clicks": 24022,
    "num_clicks_per_city": 53.860986547085204,
    "most_played_city": "Bulawayo, Zimbabwe",
    "most_played_city_num_clicks": 103
  },
  "Total": {
    "num_clicks": 374091
  }
}