{
  "\u1e28\u0101\u2019il, \u1e28\u0101\u2019il, Saudi Arabia": {
    "lats": [
      27.287,
      25.296,
      27.294,
      29.891,
      24.821,
      26.699,
      33.622,
      27.287,
      25.296,
      27.294,
      29.891,
      24.821,
      26.699,
      33.622,
      29.450020543341463,
      28.623463848578375,
      30.14318126671422,
      28.716549462196046,
      28.88671377464583,
      27.525784516591077
    ],
    "lons": [
      38.89,
      51.122,
      42.56,
      39.031,
      37.533,
      49.528,
      36.776,
      38.89,
      51.122,
      42.56,
      39.031,
      37.533,
      49.528,
      36.776,
      43.72784313725491,
      37.874179464228014,
      39.14239583333334,
      40.915111096263715,
      40.614117647058826,
      41.496339869281044
    ],
    "true_lat": 27.5236,
    "true_lon": 41.7001,
    "wiki": "https://en.wikipedia.org/wiki/Special:Search?search=\u1e28\u0101\u2019il%2C+Saudi Arabia&go=Go&ns0=1",
    "mean_dist": 546.5,
    "mean_lat": 27.844,
    "mean_lon": 42.205,
    "mean_time": 5.5,
    "std_dist": 298.9,
    "std_time": 0.6,
    "city": "\u1e28\u0101\u2019il",
    "admin": "\u1e28\u0101\u2019il",
    "country": "Saudi Arabia",
    "iso2": "SA",
    "regions": [
      "Minsk",
      "Eugene",
      "Muscat",
      "Muscat",
      "Medford",
      "Medford",
      "Medford",
      "Minsk",
      "Eugene",
      "Muscat",
      "Muscat",
      "Medford",
      "Medford",
      "Medford",
      "Quebec",
      "Hawalli",
      "Riyadh Region",
      "Medina Region",
      "Medina Region",
      "Mecca Region"
    ],
    "countries": [
      "Belarus",
      "United States",
      "Oman",
      "Oman",
      "United States",
      "United States",
      "United States",
      "Belarus",
      "United States",
      "Oman",
      "Oman",
      "United States",
      "United States",
      "United States",
      "Canada",
      "Kuwait",
      "Saudi Arabia",
      "Saudi Arabia",
      "Saudi Arabia",
      "Saudi Arabia"
    ],
    "dists": [
      278.6,
      970.2,
      88.6,
      370.2,
      512.9,
      780,
      825.5,
      278.6,
      970.2,
      88.6,
      370.2,
      512.9,
      780,
      825.5,
      291.8062837949395,
      394.7654854988872,
      383.2709729023788,
      153.3690354788568,
      185.1956847041458,
      20.09404220434197
    ],
    "times": [
      6.7,
      6.3,
      5,
      5.6,
      5.7,
      5.1,
      4.7,
      6.7,
      6.3,
      5,
      5.6,
      5.7,
      5.1,
      4.7,
      4.100000000000021,
      4.8000000000000185,
      3.633333333333356,
      2.4666666666666934,
      2.100000000000028,
      4.866666666666685
    ]
  },
  "Dhahran, Ash Sharq\u012byah, Saudi Arabia": {
    "lats": [
      31.084,
      27.554,
      31.084,
      27.554,
      24.607296270237267,
      24.387087367211443,
      21.449391538061402,
      21.47364958804378,
      25.143,
      26.287,
      23.496,
      29.013,
      26.876
    ],
    "lons": [
      38.83,
      44.748,
      38.83,
      44.748,
      50.586688444910486,
      38.19031629649643,
      39.1956426932765,
      48.04381262791702,
      50.266,
      49.784,
      47.445,
      43.25,
      46.919
    ],
    "true_lat": 26.2914,
    "true_lon": 50.1583,
    "wiki": "https://en.wikipedia.org/wiki/Special:Search?search=Dhahran%2C+Saudi Arabia&go=Go&ns0=1",
    "mean_dist": 890,
    "mean_lat": 29.319,
    "mean_lon": 41.789,
    "mean_time": 7.4,
    "std_dist": 335.7,
    "std_time": 0.4,
    "city": "Dhahran",
    "admin": "Ash Sharq\u012byah",
    "country": "Saudi Arabia",
    "iso2": "SA",
    "regions": [
      "Medford",
      "Medford",
      "Medford",
      "Medford",
      "England",
      "England",
      "England",
      "England",
      "Quebec",
      "Hawalli",
      "Riyadh Region",
      "Medina Region",
      "Mecca Region"
    ],
    "countries": [
      "United States",
      "United States",
      "United States",
      "United States",
      "United Kingdom",
      "United Kingdom",
      "United Kingdom",
      "United Kingdom",
      "Canada",
      "Kuwait",
      "Saudi Arabia",
      "Saudi Arabia",
      "Saudi Arabia"
    ],
    "dists": [
      1225.8,
      554.3,
      1225.8,
      554.3,
      192.13945553057223,
      1220.7548415038173,
      1237.2112992588955,
      577.2006353447374,
      128.1,
      37.2,
      414,
      744.4,
      328.5
    ],
    "times": [
      7.9,
      7,
      7.9,
      7,
      6.866666666666678,
      4.40000000000002,
      7.833333333333341,
      6.700000000000012,
      1.1,
      5.2,
      2.7,
      0.1,
      2.3
    ]
  },
  "Yanbu\u2018, Al Mad\u012bnah al Munawwarah, Saudi Arabia": {
    "lats": [
      22.570826815249383,
      26.772,
      22.570826815249383,
      26.772,
      20.849757948565617,
      23.61752149914372,
      23.901770511366458,
      23.96654208957757,
      24.362176227401438,
      24.812511338336904
    ],
    "lons": [
      40.4481849814963,
      45.44,
      40.4481849814963,
      45.44,
      41.39254901960784,
      38.600715411940435,
      50.53344158496732,
      38.312069035947715,
      38.226928104575165,
      38.04529411764706
    ],
    "true_lat": 24.0943,
    "true_lon": 38.0493,
    "wiki": "https://en.wikipedia.org/wiki/Special:Search?search=Yanbu\u2018%2C+Saudi Arabia&go=Go&ns0=1",
    "mean_dist": 548.6,
    "mean_lat": 24.671,
    "mean_lon": 42.944,
    "mean_time": 8.4,
    "std_dist": 250.8,
    "std_time": 0.5,
    "city": "Yanbu\u2018",
    "admin": "Al Mad\u012bnah al Munawwarah",
    "country": "Saudi Arabia",
    "iso2": "SA",
    "regions": [
      "Oakland",
      "Eugene",
      "Oakland",
      "Eugene",
      "Quebec",
      "Hawalli",
      "Riyadh Region",
      "Medina Region",
      "Medina Region",
      "Mecca Region"
    ],
    "countries": [
      "United States",
      "United States",
      "United States",
      "United States",
      "Canada",
      "Kuwait",
      "Saudi Arabia",
      "Saudi Arabia",
      "Saudi Arabia",
      "Saudi Arabia"
    ],
    "dists": [
      297.7935212438886,
      799.5,
      297.7935212438886,
      799.5,
      498.1121639941107,
      77.16952794701868,
      1267.9419172156327,
      30.231828047280725,
      34.808780286294834,
      79.86248641126672
    ],
    "times": [
      9.000000000000004,
      7.9,
      9.000000000000004,
      7.9,
      3.3666666666666902,
      5.600000000000016,
      2.3333333333333606,
      1.1666666666666925,
      3.8333333333333552,
      3.633333333333356
    ]
  },
  "Al Qurayy\u0101t, Al Jawf, Saudi Arabia": {
    "lats": [
      30.117371476872467,
      19.737,
      30.117371476872467,
      19.737,
      25.08687385467742,
      24.607,
      19.701,
      27.956,
      24.33,
      21.044,
      27.635,
      29.894,
      25.515,
      29.154,
      29.631
    ],
    "lons": [
      42.32666666666667,
      41.963,
      42.32666666666667,
      41.963,
      44.9672518382353,
      45.241,
      41.096,
      48.199,
      49.6,
      43.182,
      44.828,
      42.333,
      43.042,
      39.342,
      36.877
    ],
    "true_lat": 31.3333,
    "true_lon": 37.3333,
    "wiki": "https://en.wikipedia.org/wiki/Special:Search?search=Al Qurayy\u0101t%2C+Saudi Arabia&go=Go&ns0=1",
    "mean_dist": 933,
    "mean_lat": 24.927,
    "mean_lon": 42.144,
    "mean_time": 7.7,
    "std_dist": 436.9,
    "std_time": 0.1,
    "city": "Al Qurayy\u0101t",
    "admin": "Al Jawf",
    "country": "Saudi Arabia",
    "iso2": "SA",
    "regions": [
      "Bradford",
      "Eugene",
      "Bradford",
      "Eugene",
      "Lima",
      "England",
      "England",
      "England",
      "England",
      "Quebec",
      "Hawalli",
      "Riyadh Region",
      "Medina Region",
      "Medina Region",
      "Mecca Region"
    ],
    "countries": [
      "United Kingdom",
      "United States",
      "United Kingdom",
      "United States",
      "Peru",
      "United Kingdom",
      "United Kingdom",
      "United Kingdom",
      "United Kingdom",
      "Canada",
      "Kuwait",
      "Saudi Arabia",
      "Saudi Arabia",
      "Saudi Arabia",
      "Saudi Arabia"
    ],
    "dists": [
      496.0211978107993,
      1370,
      496.0211978107993,
      1370,
      1020.175696336162,
      1077.5,
      1347,
      1114.5,
      1434.1,
      1283.7,
      833.5,
      504.5,
      854.2,
      309.7,
      194.2
    ],
    "times": [
      7.866666666666674,
      7.7,
      7.866666666666674,
      7.7,
      8.533333333333339,
      5,
      5.5,
      5.4,
      7.1,
      1.2,
      6.1,
      3.3,
      1.1,
      0.2,
      3.7
    ]
  },
  "Al Jubayl, Ash Sharq\u012byah, Saudi Arabia": {
    "lats": [
      32.93851986095274,
      32.93851986095274,
      25.426112849060896
    ],
    "lons": [
      35.39862745098039,
      35.39862745098039,
      51.04509803921569
    ],
    "true_lat": 27.0046,
    "true_lon": 49.646,
    "wiki": "https://en.wikipedia.org/wiki/Special:Search?search=Al Jubayl%2C+Saudi Arabia&go=Go&ns0=1",
    "mean_dist": 1520.8,
    "mean_lat": 32.938,
    "mean_lon": 35.398,
    "mean_time": 4.7,
    "std_dist": 0,
    "std_time": 0,
    "city": "Al Jubayl",
    "admin": "Ash Sharq\u012byah",
    "country": "Saudi Arabia",
    "iso2": "SA",
    "regions": [
      "Bradford",
      "Bradford",
      "Riyadh Region"
    ],
    "countries": [
      "United Kingdom",
      "United Kingdom",
      "Saudi Arabia"
    ],
    "dists": [
      1520.853254268016,
      1520.853254268016,
      224.24265502573
    ],
    "times": [
      4.766666666666685,
      4.766666666666685,
      7.10000000000001
    ]
  },
  "Al Qunfudhah, , Saudi Arabia": {
    "lats": [
      25.85042502645219,
      30.184,
      27.439,
      27.675,
      25.85042502645219,
      30.184,
      27.439,
      27.675,
      18.716064243529846,
      24.71783871562816,
      27.611962751545732,
      19.823269590238294,
      24.457118035493945,
      23.814883713693966
    ],
    "lons": [
      49.701749742358345,
      36.41,
      43.435,
      41.574,
      49.701749742358345,
      36.41,
      43.435,
      41.574,
      44.532222222222224,
      29.249019607843138,
      44.90600952958749,
      41.18496732026144,
      42.170980392156864,
      40.76980392156863
    ],
    "true_lat": 19.1264,
    "true_lon": 41.0789,
    "wiki": "https://en.wikipedia.org/wiki/Special:Search?search=Al Qunfudhah%2C+Saudi Arabia&go=Go&ns0=1",
    "mean_dist": 1095.5,
    "mean_lat": 27.787,
    "mean_lon": 42.78,
    "mean_time": 4.7,
    "std_dist": 152.6,
    "std_time": 1,
    "city": "Al Qunfudhah",
    "admin": "",
    "country": "Saudi Arabia",
    "iso2": "SA",
    "regions": [
      "Minsk",
      "Eugene",
      "Muscat",
      "Muscat",
      "Minsk",
      "Eugene",
      "Muscat",
      "Muscat",
      "Riyadh Region",
      "Quebec",
      "Hawalli",
      "Mecca Region",
      "Medina Region",
      "Medina Region"
    ],
    "countries": [
      "Belarus",
      "United States",
      "Oman",
      "Oman",
      "Belarus",
      "United States",
      "Oman",
      "Oman",
      "Saudi Arabia",
      "Canada",
      "Kuwait",
      "Saudi Arabia",
      "Saudi Arabia",
      "Saudi Arabia"
    ],
    "dists": [
      1158.5629764154653,
      1316.6,
      955,
      952,
      1158.5629764154653,
      1316.6,
      955,
      952,
      366.09065137895624,
      1368.653312098288,
      1021.0040668129589,
      78.28208565911271,
      603.3667544236511,
      522.3150420686334
    ],
    "times": [
      5.666666666666682,
      5.9,
      3.3,
      4.1,
      5.666666666666682,
      5.9,
      3.3,
      4.1,
      4.433333333333353,
      6.766666666666678,
      6.433333333333346,
      5.033333333333351,
      2.2000000000000277,
      1.5666666666666937
    ]
  },
  "Al Wajh, Tab\u016bk, Saudi Arabia": {
    "lats": [
      27.287984576103216,
      27.287984576103216,
      25.872551456903828
    ],
    "lons": [
      40.87952752013612,
      40.87952752013612,
      39.40308925653595
    ],
    "true_lat": 26.2324,
    "true_lon": 36.4636,
    "wiki": "https://en.wikipedia.org/wiki/Special:Search?search=Al Wajh%2C+Saudi Arabia&go=Go&ns0=1",
    "mean_dist": 453.8,
    "mean_lat": 27.287,
    "mean_lon": 40.879,
    "mean_time": 6.1,
    "std_dist": 0,
    "std_time": 1.4,
    "city": "Al Wajh",
    "admin": "Tab\u016bk",
    "country": "Saudi Arabia",
    "iso2": "SA",
    "regions": [
      "Minsk",
      "Minsk",
      "Lima"
    ],
    "countries": [
      "Belarus",
      "Belarus",
      "Peru"
    ],
    "dists": [
      453.8467958641416,
      453.8467958641416,
      296.35181285332055
    ],
    "times": [
      6.100000000000014,
      6.100000000000014,
      10
    ]
  },
  "Al Quway\u2018\u012byah, Ar Riy\u0101\u1e11, Saudi Arabia": {
    "lats": [
      22.802881914166672,
      31.26,
      28.583,
      26.821,
      22.802881914166672,
      31.26,
      28.583,
      26.821,
      24.148296810339385,
      24.69415929188975,
      26.47443413663668,
      23.26527410579015
    ],
    "lons": [
      45.63660813015791,
      46.697,
      39.623,
      45.738,
      45.63660813015791,
      46.697,
      39.623,
      45.738,
      44.81764705882353,
      45.64797385620915,
      43.73836247076396,
      45.69986928104575
    ],
    "true_lat": 24.0737,
    "true_lon": 45.2806,
    "wiki": "https://en.wikipedia.org/wiki/Special:Search?search=Al Quway\u2018\u012byah%2C+Saudi Arabia&go=Go&ns0=1",
    "mean_dist": 505.1,
    "mean_lat": 27.366,
    "mean_lon": 44.423,
    "mean_time": 6.9,
    "std_dist": 284.2,
    "std_time": 0.8,
    "city": "Al Quway\u2018\u012byah",
    "admin": "Ar Riy\u0101\u1e11",
    "country": "Saudi Arabia",
    "iso2": "SA",
    "regions": [
      "Minsk",
      null,
      "Medford",
      "Medford",
      "Minsk",
      null,
      "Medford",
      "Medford",
      "Riyadh Region",
      "Quebec",
      "Hawalli",
      "Mecca Region"
    ],
    "countries": [
      "Belarus",
      "Iraq",
      "United States",
      "United States",
      "Belarus",
      "Iraq",
      "United States",
      "United States",
      "Saudi Arabia",
      "Canada",
      "Kuwait",
      "Saudi Arabia"
    ],
    "dists": [
      145.9011842374685,
      811.2,
      754.3,
      309,
      145.9011842374685,
      811.2,
      754.3,
      309,
      47.71337205759842,
      78.38474837122659,
      308.7128469533276,
      99.5181307099032
    ],
    "times": [
      7.20000000000001,
      5.7,
      6.8,
      8,
      7.20000000000001,
      5.7,
      6.8,
      8,
      3.666666666666689,
      1.5000000000000269,
      6.066666666666681,
      5.7333333333333485
    ]
  },
  "\u2018Ar\u2018ar, Al \u1e28ud\u016bd ash Sham\u0101l\u012byah, Saudi Arabia": {
    "lats": [
      25.18395073698383,
      22.609,
      25.18395073698383,
      22.609
    ],
    "lons": [
      49.701749742358345,
      46.104,
      49.701749742358345,
      46.104
    ],
    "true_lat": 30.99,
    "true_lon": 41.0207,
    "wiki": "https://en.wikipedia.org/wiki/Special:Search?search=\u2018Ar\u2018ar%2C+Saudi Arabia&go=Go&ns0=1",
    "mean_dist": 1063.6,
    "mean_lat": 23.896,
    "mean_lon": 47.902,
    "mean_time": 5.7,
    "std_dist": 4.3,
    "std_time": 1.4,
    "city": "\u2018Ar\u2018ar",
    "admin": "Al \u1e28ud\u016bd ash Sham\u0101l\u012byah",
    "country": "Saudi Arabia",
    "iso2": "SA",
    "regions": [
      "Minsk",
      "Grand Rapids",
      "Minsk",
      "Grand Rapids"
    ],
    "countries": [
      "Belarus",
      "United States",
      "Belarus",
      "United States"
    ],
    "dists": [
      1067.9812313522,
      1059.3,
      1067.9812313522,
      1059.3
    ],
    "times": [
      4.366666666666687,
      7.2,
      4.366666666666687,
      7.2
    ]
  },
  "A\u0163 \u0162\u0101\u2019if, Makkah al Mukarramah, Saudi Arabia": {
    "lats": [
      17.95872563116908,
      17.95872563116908,
      18.62552105497286,
      29.949240325814234,
      26.0522186293545,
      22.440620396936147,
      27.987
    ],
    "lons": [
      42.566128827325656,
      42.566128827325656,
      43.0099564187667,
      40.34397642721538,
      40.93413942530265,
      43.1137472684399,
      43.935
    ],
    "true_lat": 21.2622,
    "true_lon": 40.3823,
    "wiki": "https://en.wikipedia.org/wiki/Special:Search?search=A\u0163 \u0162\u0101\u2019if%2C+Saudi Arabia&go=Go&ns0=1",
    "mean_dist": 432.7,
    "mean_lat": 17.958,
    "mean_lon": 42.566,
    "mean_time": 4.4,
    "std_dist": 0,
    "std_time": 0,
    "city": "A\u0163 \u0162\u0101\u2019if",
    "admin": "Makkah al Mukarramah",
    "country": "Saudi Arabia",
    "iso2": "SA",
    "regions": [
      "Minsk",
      "Minsk",
      "England",
      "England",
      "England",
      "England",
      "Riyadh Region"
    ],
    "countries": [
      "Belarus",
      "Belarus",
      "United Kingdom",
      "United Kingdom",
      "United Kingdom",
      "United Kingdom",
      "Saudi Arabia"
    ],
    "dists": [
      432.7064083376202,
      432.7064083376202,
      401.7152574917058,
      965.9624310814664,
      535.580354004777,
      310.85701598701905,
      829.4
    ],
    "times": [
      4.433333333333353,
      4.433333333333353,
      2.233333333333361,
      5.933333333333348,
      6.766666666666678,
      5.766666666666682,
      4.7
    ]
  },
  "Buraydah, Al Qa\u015f\u012bm, Saudi Arabia": {
    "lats": [
      27.287984576103216,
      25.273,
      20.445,
      21.76,
      27.287984576103216,
      25.273,
      20.445,
      21.76,
      25.363321502387013,
      24.197027386504704,
      17.245101653453922,
      27.363,
      30.421,
      27.727,
      29.608,
      27.085,
      26.153
    ],
    "lons": [
      40.79303514540845,
      50.941,
      39.948,
      48.026,
      40.79303514540845,
      50.941,
      39.948,
      48.026,
      44.77440086321114,
      39.409858780156554,
      42.67263615732879,
      40.795,
      40.38,
      42.233,
      38.901,
      38.875,
      42.949
    ],
    "true_lat": 26.3664,
    "true_lon": 43.9628,
    "wiki": "https://en.wikipedia.org/wiki/Special:Search?search=Buraydah%2C+Saudi Arabia&go=Go&ns0=1",
    "mean_dist": 618,
    "mean_lat": 23.691,
    "mean_lon": 44.927,
    "mean_time": 6.2,
    "std_dist": 171,
    "std_time": 0.7,
    "city": "Buraydah",
    "admin": "Al Qa\u015f\u012bm",
    "country": "Saudi Arabia",
    "iso2": "SA",
    "regions": [
      "Minsk",
      "Eugene",
      "Medford",
      "Medford",
      "Minsk",
      "Eugene",
      "Medford",
      "Medford",
      "England",
      "England",
      "England",
      "Riyadh Region",
      "Quebec",
      "Hawalli",
      "Mecca Region",
      "Medina Region",
      "Medina Region"
    ],
    "countries": [
      "Belarus",
      "United States",
      "United States",
      "United States",
      "Belarus",
      "United States",
      "United States",
      "United States",
      "United Kingdom",
      "United Kingdom",
      "United Kingdom",
      "Saudi Arabia",
      "Canada",
      "Kuwait",
      "Saudi Arabia",
      "Saudi Arabia",
      "Saudi Arabia"
    ],
    "dists": [
      330.78619759973554,
      708.9,
      775.2,
      657.5,
      330.78619759973554,
      708.9,
      775.2,
      657.5,
      137.9659044050735,
      517.3811498029422,
      1022.9234126064623,
      333.1,
      570.9,
      228.5,
      613.8,
      511.4,
      103.7
    ],
    "times": [
      4.933333333333351,
      6.4,
      6.8,
      6.9,
      4.933333333333351,
      6.4,
      6.8,
      6.9,
      4.666666666666686,
      5.900000000000015,
      3.1333333333333577,
      5.4,
      3.1,
      5.5,
      6.5,
      4.7,
      4.1
    ]
  },
  "Sak\u0101k\u0101, Al Jawf, Saudi Arabia": {
    "lats": [
      29.239246577175415,
      27.207,
      19.344,
      29.239246577175415,
      27.207,
      19.344
    ],
    "lons": [
      39.92811139813176,
      48.82,
      41.47,
      39.92811139813176,
      48.82,
      41.47
    ],
    "true_lat": 30,
    "true_lon": 40.1333,
    "wiki": "https://en.wikipedia.org/wiki/Special:Search?search=Sak\u0101k\u0101%2C+Saudi Arabia&go=Go&ns0=1",
    "mean_dist": 727.3,
    "mean_lat": 25.263,
    "mean_lon": 43.406,
    "mean_time": 3.9,
    "std_dist": 468,
    "std_time": 0.9,
    "city": "Sak\u0101k\u0101",
    "admin": "Al Jawf",
    "country": "Saudi Arabia",
    "iso2": "SA",
    "regions": [
      "Minsk",
      "Muscat",
      "Muscat",
      "Minsk",
      "Muscat",
      "Muscat"
    ],
    "countries": [
      "Belarus",
      "Oman",
      "Oman",
      "Belarus",
      "Oman",
      "Oman"
    ],
    "dists": [
      86.88606361621245,
      902.7,
      1192.4,
      86.88606361621245,
      902.7,
      1192.4
    ],
    "times": [
      5.2666666666666835,
      3,
      3.7,
      5.2666666666666835,
      3,
      3.7
    ]
  },
  "Al Huf\u016bf, Ash Sharq\u012byah, Saudi Arabia": {
    "lats": [
      26.43539101213176,
      26.43539101213176
    ],
    "lons": [
      49.788242117086014,
      49.788242117086014
    ],
    "true_lat": 25.3487,
    "true_lon": 49.5856,
    "wiki": "https://en.wikipedia.org/wiki/Special:Search?search=Al Huf\u016bf%2C+Saudi Arabia&go=Go&ns0=1",
    "mean_dist": 122.5,
    "mean_lat": 26.435,
    "mean_lon": 49.788,
    "mean_time": 6.4,
    "std_dist": 0,
    "std_time": 1.2,
    "city": "Al Huf\u016bf",
    "admin": "Ash Sharq\u012byah",
    "country": "Saudi Arabia",
    "iso2": "SA",
    "regions": [
      "Minsk",
      "Minsk"
    ],
    "countries": [
      "Belarus",
      "Belarus"
    ],
    "dists": [
      122.52294181220455,
      122.52294181220455
    ],
    "times": [
      6.400000000000013,
      6.400000000000013
    ]
  },
  "Abh\u0101, \u2018As\u012br, Saudi Arabia": {
    "lats": [
      18.16523277420027,
      31.327,
      25.509,
      27.523,
      18.16523277420027,
      31.327,
      25.509,
      27.523,
      33.79835992704554,
      17.957,
      26.505,
      25.535,
      26.519,
      18.295,
      20.264,
      28.469,
      17.867,
      18.666,
      20.337,
      20.068,
      31.026,
      17.917,
      18.682,
      18.873,
      18.221,
      20.483
    ],
    "lons": [
      41.65795889268514,
      35.943,
      41.461,
      38.91,
      41.65795889268514,
      35.943,
      41.461,
      38.91,
      40.285311478758175,
      42.672,
      38.787,
      46.642,
      46.824,
      47.204,
      44.168,
      44.194,
      42.596,
      41.911,
      41.911,
      44.324,
      39.057,
      42.752,
      45.785,
      42.178,
      42.119,
      41.807
    ],
    "true_lat": 18.2301,
    "true_lon": 42.5001,
    "wiki": "https://en.wikipedia.org/wiki/Special:Search?search=Abh\u0101%2C+Saudi Arabia&go=Go&ns0=1",
    "mean_dist": 900.2,
    "mean_lat": 25.631,
    "mean_lon": 39.492,
    "mean_time": 6.8,
    "std_dist": 545.6,
    "std_time": 0.9,
    "city": "Abh\u0101",
    "admin": "\u2018As\u012br",
    "country": "Saudi Arabia",
    "iso2": "SA",
    "regions": [
      "Minsk",
      "Eugene",
      "Medford",
      "Medford",
      "Minsk",
      "Eugene",
      "Medford",
      "Medford",
      "Lima",
      "England",
      "England",
      "England",
      "England",
      "Riyadh Region",
      "Riyadh Region",
      "Quebec",
      "Hawalli",
      "Mecca Region",
      "Medina Region",
      "Medina Region",
      "Quebec",
      "Hawalli",
      "Riyadh Region",
      "Medina Region",
      "Medina Region",
      "Mecca Region"
    ],
    "countries": [
      "Belarus",
      "United States",
      "United States",
      "United States",
      "Belarus",
      "United States",
      "United States",
      "United States",
      "Peru",
      "United Kingdom",
      "United Kingdom",
      "United Kingdom",
      "United Kingdom",
      "Saudi Arabia",
      "Saudi Arabia",
      "Canada",
      "Kuwait",
      "Saudi Arabia",
      "Saudi Arabia",
      "Saudi Arabia",
      "Canada",
      "Kuwait",
      "Saudi Arabia",
      "Saudi Arabia",
      "Saudi Arabia",
      "Saudi Arabia"
    ],
    "dists": [
      89.25015659231671,
      1598.7,
      816.4,
      1096.6,
      89.25015659231671,
      1598.7,
      816.4,
      1096.6,
      1745.0532828438625,
      35.3,
      996,
      917.7,
      1023.1,
      496.8,
      286,
      1151.5,
      41.5,
      78.8,
      242.3,
      280.1,
      1464.5,
      43.8,
      350.1,
      79.1,
      40.2,
      260.9
    ],
    "times": [
      5.300000000000017,
      7.3,
      7.1,
      7.7,
      5.300000000000017,
      7.3,
      7.1,
      7.7,
      9.766666666666667,
      5.7,
      5.6,
      6.2,
      7.7,
      2.6,
      5.7,
      4.6,
      6.3,
      3.2,
      1.9,
      7.5,
      4.3,
      7.5,
      2.7,
      3.2,
      1.2,
      5.2
    ]
  },
  "J\u0101z\u0101n, J\u0101z\u0101n, Saudi Arabia": {
    "lats": [
      24.078271765845876,
      27.529,
      20.769,
      24.078271765845876,
      27.529,
      20.769,
      22.721402794239882,
      27.803946888915902,
      28.370038548298503,
      22.633218607221774,
      18.221,
      19.577,
      17.843,
      20.312,
      19.356,
      17.328
    ],
    "lons": [
      51.258612487456375,
      44.921,
      54.137,
      51.258612487456375,
      44.921,
      54.137,
      40.72655772595624,
      36.503714989306886,
      35.069956418766694,
      41.50498909850526,
      46.115,
      52.005,
      42.959,
      41.366,
      41.781,
      42.663
    ],
    "true_lat": 16.9066,
    "true_lon": 42.5566,
    "wiki": "https://en.wikipedia.org/wiki/Special:Search?search=J\u0101z\u0101n%2C+Saudi Arabia&go=Go&ns0=1",
    "mean_dist": 1234.7,
    "mean_lat": 24.125,
    "mean_lon": 50.105,
    "mean_time": 5.4,
    "std_dist": 40.2,
    "std_time": 0.3,
    "city": "J\u0101z\u0101n",
    "admin": "J\u0101z\u0101n",
    "country": "Saudi Arabia",
    "iso2": "SA",
    "regions": [
      "Minsk",
      "Medford",
      "Medford",
      "Minsk",
      "Medford",
      "Medford",
      "England",
      "England",
      "England",
      "England",
      "Riyadh Region",
      "Quebec",
      "Hawalli",
      "Mecca Region",
      "Medina Region",
      "Medina Region"
    ],
    "countries": [
      "Belarus",
      "United States",
      "United States",
      "Belarus",
      "United States",
      "United States",
      "United Kingdom",
      "United Kingdom",
      "United Kingdom",
      "United Kingdom",
      "Saudi Arabia",
      "Canada",
      "Kuwait",
      "Saudi Arabia",
      "Saudi Arabia",
      "Saudi Arabia"
    ],
    "dists": [
      1206.5455369812653,
      1205.9,
      1291.7,
      1206.5455369812653,
      1205.9,
      1291.7,
      674.2908134816292,
      1361.5934770036374,
      1487.2840434554485,
      646.1983718921205,
      404.5,
      1040.8,
      112.5,
      398.9,
      284.4,
      48.2
    ],
    "times": [
      5.933333333333348,
      5,
      5.3,
      5.933333333333348,
      5,
      5.3,
      2.4666666666666934,
      5.133333333333351,
      6.833333333333345,
      7.633333333333342,
      7.3,
      7.8,
      7.4,
      6.8,
      7.8,
      5.5
    ]
  },
  "Raf\u1e29\u0101, Al \u1e28ud\u016bd ash Sham\u0101l\u012byah, Saudi Arabia": {
    "lats": [
      23.205,
      31.577,
      31.104,
      23.964,
      25.869,
      23.205,
      31.577,
      31.104,
      23.964,
      25.869,
      19.34030101965103,
      18.88999913174231,
      18.70783507358794,
      20.79291077120374,
      30.713,
      30.869,
      31.599,
      18.691,
      22.304,
      28.583,
      26.427,
      31.641,
      20.224,
      27.871
    ],
    "lons": [
      57.973,
      38.959,
      38.097,
      52.129,
      51.235,
      57.973,
      38.959,
      38.097,
      52.129,
      51.235,
      42.33531589589088,
      43.094433943555245,
      43.3732243926229,
      43.91812635340722,
      39.524,
      40.121,
      39.975,
      41.34,
      45.051,
      47.438,
      44.568,
      38.182,
      42.152,
      38.953
    ],
    "true_lat": 29.6202,
    "true_lon": 43.4948,
    "wiki": "https://en.wikipedia.org/wiki/Special:Search?search=Raf\u1e29\u0101%2C+Saudi Arabia&go=Go&ns0=1",
    "mean_dist": 913.2,
    "mean_lat": 27.143,
    "mean_lon": 47.678,
    "mean_time": 5,
    "std_dist": 406.2,
    "std_time": 2,
    "city": "Raf\u1e29\u0101",
    "admin": "Al \u1e28ud\u016bd ash Sham\u0101l\u012byah",
    "country": "Saudi Arabia",
    "iso2": "SA",
    "regions": [
      "Eugene",
      "Muscat",
      "Muscat",
      "Medford",
      "Medford",
      "Eugene",
      "Muscat",
      "Muscat",
      "Medford",
      "Medford",
      "England",
      "England",
      "England",
      "England",
      "Riyadh Region",
      "Quebec",
      "Hawalli",
      "Mecca Region",
      "Medina Region",
      "Quebec",
      "Hawalli",
      "Riyadh Region",
      "Medina Region",
      "Medina Region"
    ],
    "countries": [
      "United States",
      "Oman",
      "Oman",
      "United States",
      "United States",
      "United States",
      "Oman",
      "Oman",
      "United States",
      "United States",
      "United Kingdom",
      "United Kingdom",
      "United Kingdom",
      "United Kingdom",
      "Saudi Arabia",
      "Canada",
      "Kuwait",
      "Saudi Arabia",
      "Saudi Arabia",
      "Canada",
      "Kuwait",
      "Saudi Arabia",
      "Saudi Arabia",
      "Saudi Arabia"
    ],
    "dists": [
      1606.7,
      485.4,
      543.4,
      1062.4,
      868.1,
      1606.7,
      485.4,
      543.4,
      1062.4,
      868.1,
      1149.053208478749,
      1193.8308312326858,
      1213.461998592183,
      982.4702803853984,
      400.5,
      352.5,
      402.2,
      1234.6,
      828.2,
      400,
      370.2,
      555.6,
      1053.5,
      483.4
    ],
    "times": [
      4.8,
      3.4,
      2.5,
      7.1,
      7.6,
      4.8,
      3.4,
      2.5,
      7.1,
      7.6,
      5.100000000000017,
      4.900000000000018,
      4.666666666666686,
      6.16666666666668,
      4.2,
      5.6,
      1.5,
      2.6,
      9.3,
      2,
      7.4,
      1.8,
      0.8,
      0.8
    ]
  },
  "Riyadh, Ar Riy\u0101\u1e11, Saudi Arabia": {
    "lats": [
      28.457,
      25.072,
      23.683,
      28.457,
      25.072,
      23.683
    ],
    "lons": [
      37.085,
      48.138,
      45.647,
      37.085,
      48.138,
      45.647
    ],
    "true_lat": 24.6408,
    "true_lon": 46.7727,
    "wiki": "https://en.wikipedia.org/wiki/Special:Search?search=Riyadh%2C+Saudi Arabia&go=Go&ns0=1",
    "mean_dist": 451.4,
    "mean_lat": 25.737,
    "mean_lon": 43.623,
    "mean_time": 4.8,
    "std_dist": 424.9,
    "std_time": 2.1,
    "city": "Riyadh",
    "admin": "Ar Riy\u0101\u1e11",
    "country": "Saudi Arabia",
    "iso2": "SA",
    "regions": [
      "Eugene",
      "Muscat",
      "Muscat",
      "Eugene",
      "Muscat",
      "Muscat"
    ],
    "countries": [
      "United States",
      "Oman",
      "Oman",
      "United States",
      "Oman",
      "Oman"
    ],
    "dists": [
      1052.4,
      145.9,
      156,
      1052.4,
      145.9,
      156
    ],
    "times": [
      1.9,
      5.3,
      7.2,
      1.9,
      5.3,
      7.2
    ]
  },
  "Dawmat al Jandal, Al Jawf, Saudi Arabia": {
    "lats": [],
    "lons": [],
    "true_lat": 29.8153,
    "true_lon": 39.8664,
    "wiki": "https://en.wikipedia.org/wiki/Special:Search?search=Dawmat al Jandal%2C+Saudi Arabia&go=Go&ns0=1",
    "regions": [],
    "countries": [],
    "dists": [],
    "times": []
  },
  "Al Qa\u0163\u012bf, Ash Sharq\u012byah, Saudi Arabia": {
    "lats": [
      23.767,
      24.966,
      23.767,
      24.966
    ],
    "lons": [
      39.219,
      50.266,
      39.219,
      50.266
    ],
    "true_lat": 26.5196,
    "true_lon": 50.0115,
    "wiki": "https://en.wikipedia.org/wiki/Special:Search?search=Al Qa\u0163\u012bf%2C+Saudi Arabia&go=Go&ns0=1",
    "mean_dist": 651.3,
    "mean_lat": 24.366,
    "mean_lon": 44.742,
    "mean_time": 4,
    "std_dist": 476.7,
    "std_time": 0.9,
    "city": "Al Qa\u0163\u012bf",
    "admin": "Ash Sharq\u012byah",
    "country": "Saudi Arabia",
    "iso2": "SA",
    "regions": [
      "Muscat",
      "Muscat",
      "Muscat",
      "Muscat"
    ],
    "countries": [
      "Oman",
      "Oman",
      "Oman",
      "Oman"
    ],
    "dists": [
      1128.1,
      174.6,
      1128.1,
      174.6
    ],
    "times": [
      3.1,
      5,
      3.1,
      5
    ]
  },
  "Najr\u0101n, Najr\u0101n, Saudi Arabia": {
    "lats": [
      24.035,
      27.143,
      28.094,
      18.215,
      24.035,
      27.143,
      28.094,
      18.215,
      19.118801684423733,
      28.470504400939934,
      23.233342511009038,
      23.25729194675631,
      18.469,
      17.973,
      21.772,
      19.005,
      19.577,
      30.69,
      17.171,
      17.965,
      17.809,
      18.444,
      17.849
    ],
    "lons": [
      40.873,
      36.592,
      35.335,
      41.983,
      40.873,
      36.592,
      35.335,
      41.983,
      41.84230935994317,
      38.709270544862434,
      43.65864922922421,
      52.921982562557545,
      48.268,
      46.14,
      52.861,
      43.79,
      42.352,
      40.224,
      42.726,
      44.461,
      45.759,
      42.352,
      44.143
    ],
    "true_lat": 17.5065,
    "true_lon": 44.1316,
    "wiki": "https://en.wikipedia.org/wiki/Special:Search?search=Najr\u0101n%2C+Saudi Arabia&go=Go&ns0=1",
    "mean_dist": 961.2,
    "mean_lat": 24.371,
    "mean_lon": 38.695,
    "mean_time": 3.8,
    "std_dist": 486.2,
    "std_time": 2.6,
    "city": "Najr\u0101n",
    "admin": "Najr\u0101n",
    "country": "Saudi Arabia",
    "iso2": "SA",
    "regions": [
      "Muscat",
      "Muscat",
      "Medford",
      "Medford",
      "Muscat",
      "Muscat",
      "Medford",
      "Medford",
      "England",
      "England",
      "England",
      "England",
      "Riyadh Region",
      "Riyadh Region",
      "Quebec",
      "Hawalli",
      "Mecca Region",
      "Quebec",
      "Hawalli",
      "Riyadh Region",
      "Medina Region",
      "Medina Region",
      "Mecca Region"
    ],
    "countries": [
      "Oman",
      "Oman",
      "United States",
      "United States",
      "Oman",
      "Oman",
      "United States",
      "United States",
      "United Kingdom",
      "United Kingdom",
      "United Kingdom",
      "United Kingdom",
      "Saudi Arabia",
      "Saudi Arabia",
      "Canada",
      "Kuwait",
      "Saudi Arabia",
      "Canada",
      "Kuwait",
      "Saudi Arabia",
      "Saudi Arabia",
      "Saudi Arabia",
      "Saudi Arabia"
    ],
    "dists": [
      800.9,
      1321.9,
      1481.6,
      240.6,
      800.9,
      1321.9,
      1481.6,
      240.6,
      300.89478330794833,
      1338.9937608543257,
      638.6991938248655,
      1116.7919407888362,
      450.4,
      219,
      1029.6,
      170.5,
      297,
      1518.3,
      153.7,
      61.8,
      175.6,
      215.1,
      38.1
    ],
    "times": [
      0.2,
      4.9,
      2.7,
      7.5,
      0.2,
      4.9,
      2.7,
      7.5,
      2.6333333333333595,
      6.300000000000013,
      6.26666666666668,
      7.1333333333333435,
      5.9,
      4.8,
      6,
      7.2,
      7.2,
      3.9,
      7.1,
      6.3,
      2.5,
      1.8,
      5
    ]
  },
  "Medina, Al Mad\u012bnah al Munawwarah, Saudi Arabia": {
    "lats": [
      21.331364864118644,
      25.543,
      23.085,
      27.196,
      29.123,
      21.331364864118644,
      25.543,
      23.085,
      27.196,
      29.123
    ],
    "lons": [
      53.332898565491824,
      39.835,
      41.781,
      49.354,
      39.49,
      53.332898565491824,
      39.835,
      41.781,
      49.354,
      39.49
    ],
    "true_lat": 24.5,
    "true_lon": 39.58,
    "wiki": "https://en.wikipedia.org/wiki/Special:Search?search=Medina%2C+Saudi Arabia&go=Go&ns0=1",
    "mean_dist": 676,
    "mean_lat": 25.255,
    "mean_lon": 44.758,
    "mean_time": 4.9,
    "std_dist": 493.8,
    "std_time": 2.3,
    "city": "Medina",
    "admin": "Al Mad\u012bnah al Munawwarah",
    "country": "Saudi Arabia",
    "iso2": "SA",
    "regions": [
      "Grand Rapids",
      "Muscat",
      "Muscat",
      "Medford",
      "Medford",
      "Grand Rapids",
      "Muscat",
      "Muscat",
      "Medford",
      "Medford"
    ],
    "countries": [
      "United States",
      "Oman",
      "Oman",
      "United States",
      "United States",
      "United States",
      "Oman",
      "Oman",
      "United States",
      "United States"
    ],
    "dists": [
      1451.1924254907597,
      118.8,
      273.7,
      1022.6,
      514.2,
      1451.1924254907597,
      118.8,
      273.7,
      1022.6,
      514.2
    ],
    "times": [
      6.333333333333346,
      3.8,
      4,
      1.9,
      8.6,
      6.333333333333346,
      3.8,
      4,
      1.9,
      8.6
    ]
  },
  "Al Mubarraz, Ash Sharq\u012byah, Saudi Arabia": {
    "lats": [
      27.929547121472986,
      27.929547121472986,
      25.09609478893282,
      26.85342274707268,
      26.42776078534673,
      25.802172356266947
    ],
    "lons": [
      41.885555555555555,
      41.885555555555555,
      48.969281045751636,
      48.83954248366013,
      49.0835912289339,
      40.79575163398693
    ],
    "true_lat": 25.4291,
    "true_lon": 49.5659,
    "wiki": "https://en.wikipedia.org/wiki/Special:Search?search=Al Mubarraz%2C+Saudi Arabia&go=Go&ns0=1",
    "mean_dist": 811.9,
    "mean_lat": 27.929,
    "mean_lon": 41.885,
    "mean_time": 6.6,
    "std_dist": 0,
    "std_time": 0,
    "city": "Al Mubarraz",
    "admin": "Ash Sharq\u012byah",
    "country": "Saudi Arabia",
    "iso2": "SA",
    "regions": [
      "Eugene",
      "Eugene",
      "Riyadh Region",
      "Quebec",
      "Hawalli",
      "Mecca Region"
    ],
    "countries": [
      "United States",
      "United States",
      "Saudi Arabia",
      "Canada",
      "Kuwait",
      "Saudi Arabia"
    ],
    "dists": [
      811.9571438923798,
      811.9571438923798,
      70.5027275910298,
      174.1838312515832,
      121.0678781402502,
      880.1632195165453
    ],
    "times": [
      6.6666666666666785,
      6.6666666666666785,
      3.8666666666666885,
      0.6333333333333587,
      1.133333333333359,
      1.8333333333333612
    ]
  },
  "Al B\u0101\u1e29ah, Al B\u0101\u1e29ah, Saudi Arabia": {
    "lats": [
      30.992748074539662,
      18.82,
      29.981,
      22.132,
      21.536,
      30.992748074539662,
      18.82,
      29.981,
      22.132,
      21.536
    ],
    "lons": [
      36.64411764705882,
      41.781,
      38.979,
      53.967,
      46.182,
      36.64411764705882,
      41.781,
      38.979,
      53.967,
      46.182
    ],
    "true_lat": 20.0129,
    "true_lon": 41.4677,
    "wiki": "https://en.wikipedia.org/wiki/Special:Search?search=Al B\u0101\u1e29ah%2C+Saudi Arabia&go=Go&ns0=1",
    "mean_dist": 884.4,
    "mean_lat": 24.692,
    "mean_lon": 43.51,
    "mean_time": 6,
    "std_dist": 474.9,
    "std_time": 1.8,
    "city": "Al B\u0101\u1e29ah",
    "admin": "Al B\u0101\u1e29ah",
    "country": "Saudi Arabia",
    "iso2": "SA",
    "regions": [
      "Eugene",
      "Muscat",
      "Muscat",
      "Medford",
      "Medford",
      "Eugene",
      "Muscat",
      "Muscat",
      "Medford",
      "Medford"
    ],
    "countries": [
      "United States",
      "Oman",
      "Oman",
      "United States",
      "United States",
      "United States",
      "Oman",
      "Oman",
      "United States",
      "United States"
    ],
    "dists": [
      1312.9054701274767,
      136.5,
      1136.4,
      1317.7,
      518.6,
      1312.9054701274767,
      136.5,
      1136.4,
      1317.7,
      518.6
    ],
    "times": [
      7.500000000000009,
      2.8,
      5.1,
      7.5,
      7.4,
      7.500000000000009,
      2.8,
      5.1,
      7.5,
      7.4
    ]
  },
  "Mecca, Makkah al Mukarramah, Saudi Arabia": {
    "lats": [
      24.08882212843313,
      22.629,
      24.705,
      24.08882212843313,
      22.629,
      24.705,
      20.06828758264763,
      20.208504362225607,
      21.351790233794027,
      23.188625396881395,
      23.981698147220165,
      22.785501079422115
    ],
    "lons": [
      41.885555555555555,
      39.738,
      39.654,
      41.885555555555555,
      39.738,
      39.654,
      40.69196078431372,
      41.325225215862005,
      41.659323937908496,
      39.30635292632907,
      39.03130718954249,
      39.08320261437909
    ],
    "true_lat": 21.43,
    "true_lon": 39.82,
    "wiki": "https://en.wikipedia.org/wiki/Special:Search?search=Mecca%2C+Saudi Arabia&go=Go&ns0=1",
    "mean_dist": 287.2,
    "mean_lat": 23.807,
    "mean_lon": 40.425,
    "mean_time": 6.1,
    "std_dist": 108.6,
    "std_time": 2.2,
    "city": "Mecca",
    "admin": "Makkah al Mukarramah",
    "country": "Saudi Arabia",
    "iso2": "SA",
    "regions": [
      "Eugene",
      "Muscat",
      "Muscat",
      "Eugene",
      "Muscat",
      "Muscat",
      "Quebec",
      "Hawalli",
      "Riyadh Region",
      "Medina Region",
      "Medina Region",
      "Mecca Region"
    ],
    "countries": [
      "United States",
      "Oman",
      "Oman",
      "United States",
      "Oman",
      "Oman",
      "Canada",
      "Kuwait",
      "Saudi Arabia",
      "Saudi Arabia",
      "Saudi Arabia",
      "Saudi Arabia"
    ],
    "dists": [
      363.6645831667701,
      133.6,
      364.6,
      363.6645831667701,
      133.6,
      364.6,
      176.48498588151972,
      207.17556665453475,
      190.6320009041259,
      202.5625811747693,
      295.041527401985,
      168.75743524696122
    ],
    "times": [
      8.700000000000005,
      3.2,
      6.5,
      8.700000000000005,
      3.2,
      6.5,
      5.833333333333348,
      5.700000000000015,
      1.200000000000026,
      2.266666666666694,
      2.43333333333336,
      3.633333333333356
    ]
  },
  "Tab\u016bk, Tab\u016bk, Saudi Arabia": {
    "lats": [
      28.932348122946443,
      29.188666569297748,
      28.932348122946443,
      29.188666569297748,
      27.948736556175252,
      25.356630132465018,
      28.20937356998397,
      26.0522186293545,
      29.88,
      19.847,
      31.376,
      26.597,
      25.496,
      27.871,
      31.382,
      28.943,
      29.94,
      28.212,
      30.713,
      28.56
    ],
    "lons": [
      37.435522875817,
      43.5202614379085,
      37.435522875817,
      43.5202614379085,
      37.820413935106565,
      37.2302509370193,
      34.99211328151179,
      43.165642693276496,
      37.344,
      42.067,
      37.77,
      37.396,
      40.821,
      37.448,
      39.757,
      36.914,
      37.507,
      37.412,
      39.368,
      37.889
    ],
    "true_lat": 28.3838,
    "true_lon": 36.555,
    "wiki": "https://en.wikipedia.org/wiki/Special:Search?search=Tab\u016bk%2C+Saudi Arabia&go=Go&ns0=1",
    "mean_dist": 394.9,
    "mean_lat": 29.06,
    "mean_lon": 40.477,
    "mean_time": 2.8,
    "std_dist": 289.5,
    "std_time": 0.3,
    "city": "Tab\u016bk",
    "admin": "Tab\u016bk",
    "country": "Saudi Arabia",
    "iso2": "SA",
    "regions": [
      "Muscat",
      "Muscat",
      "Muscat",
      "Muscat",
      "England",
      "England",
      "England",
      "England",
      "Riyadh Region",
      "Quebec",
      "Hawalli",
      "Mecca Region",
      "Medina Region",
      "Medina Region",
      "Quebec",
      "Hawalli",
      "Riyadh Region",
      "Medina Region",
      "Medina Region",
      "Mecca Region"
    ],
    "countries": [
      "Oman",
      "Oman",
      "Oman",
      "Oman",
      "United Kingdom",
      "United Kingdom",
      "United Kingdom",
      "United Kingdom",
      "Saudi Arabia",
      "Canada",
      "Kuwait",
      "Saudi Arabia",
      "Saudi Arabia",
      "Saudi Arabia",
      "Canada",
      "Kuwait",
      "Saudi Arabia",
      "Saudi Arabia",
      "Saudi Arabia",
      "Saudi Arabia"
    ],
    "dists": [
      105.36514176565888,
      684.5585075843534,
      105.36514176565888,
      684.5585075843534,
      133.14375930278842,
      343.2021576655635,
      154.24185750916777,
      703.0683416849729,
      183.2,
      1101.3,
      352.8,
      215.2,
      530.9,
      104.4,
      454.4,
      71.4,
      196.2,
      86,
      375.6,
      131.9
    ],
    "times": [
      2.5000000000000266,
      3.166666666666691,
      2.5000000000000266,
      3.166666666666691,
      2.833333333333359,
      6.533333333333346,
      5.000000000000018,
      3.766666666666689,
      4.4,
      1.5,
      5.7,
      3.5,
      0.3,
      4.6,
      3,
      4.5,
      5.7,
      4.1,
      2.2,
      4.1
    ]
  },
  "Jeddah, Makkah al Mukarramah, Saudi Arabia": {
    "lats": [
      25.835693543883266,
      26.668765896501842,
      25.835693543883266,
      26.668765896501842,
      32.15854592657069,
      25.119,
      22.785,
      20.77,
      23.432,
      25.989
    ],
    "lons": [
      37.46145423134947,
      37.44218050864869,
      37.46145423134947,
      37.44218050864869,
      36.938056576797386,
      37.733,
      39.29,
      40.572,
      38.745,
      48.476
    ],
    "true_lat": 21.5169,
    "true_lon": 39.2192,
    "wiki": "https://en.wikipedia.org/wiki/Special:Search?search=Jeddah%2C+Saudi Arabia&go=Go&ns0=1",
    "mean_dist": 556.5,
    "mean_lat": 26.252,
    "mean_lon": 37.451,
    "mean_time": 7.2,
    "std_dist": 44,
    "std_time": 0.3,
    "city": "Jeddah",
    "admin": "Makkah al Mukarramah",
    "country": "Saudi Arabia",
    "iso2": "SA",
    "regions": [
      "Medford",
      "Medford",
      "Medford",
      "Medford",
      "Lima",
      "Riyadh Region",
      "Quebec",
      "Hawalli",
      "Mecca Region",
      "Medina Region"
    ],
    "countries": [
      "United States",
      "United States",
      "United States",
      "United States",
      "Peru",
      "Saudi Arabia",
      "Canada",
      "Kuwait",
      "Saudi Arabia",
      "Saudi Arabia"
    ],
    "dists": [
      512.4801195304568,
      600.5599847939584,
      512.4801195304568,
      600.5599847939584,
      1204.6390354793532,
      428.3,
      141.2,
      163,
      218.5,
      1064.8
    ],
    "times": [
      6.900000000000011,
      7.533333333333342,
      6.900000000000011,
      7.533333333333342,
      8.600000000000005,
      5.9,
      4.9,
      6.2,
      2.7,
      3.3
    ]
  },
  "Qal\u2018at B\u012bshah, , Saudi Arabia": {
    "lats": [
      33.12426547454931,
      20.174,
      27.896,
      25.888,
      22.633,
      22.953,
      18.536,
      19.47,
      19.45,
      25.072,
      20.41
    ],
    "lons": [
      44.05908190359477,
      42.516,
      37.1,
      36.834,
      39.273,
      51.901,
      42.544,
      47.004,
      43.224,
      45.829,
      41.677
    ],
    "true_lat": 20.0087,
    "true_lon": 42.5987,
    "wiki": "https://en.wikipedia.org/wiki/Special:Search?search=Qal\u2018at B\u012bshah%2C+Saudi Arabia&go=Go&ns0=1",
    "mean_dist": 577.4,
    "mean_lat": 23.236,
    "mean_lon": 42.905,
    "mean_time": 3.8,
    "std_dist": 453.4,
    "std_time": 2,
    "city": "Qal\u2018at B\u012bshah",
    "admin": "",
    "country": "Saudi Arabia",
    "iso2": "SA",
    "regions": [
      "Lima",
      "England",
      "England",
      "England",
      "England",
      "Quebec",
      "Hawalli",
      "Riyadh Region",
      "Medina Region",
      "Medina Region",
      "Mecca Region"
    ],
    "countries": [
      "Peru",
      "United Kingdom",
      "United Kingdom",
      "United Kingdom",
      "United Kingdom",
      "Canada",
      "Kuwait",
      "Saudi Arabia",
      "Saudi Arabia",
      "Saudi Arabia",
      "Saudi Arabia"
    ],
    "dists": [
      1465.543646598958,
      20.3,
      1039.4,
      880.4,
      451.4,
      1016.4,
      163.8,
      464.9,
      90.2,
      653.4,
      105.9
    ],
    "times": [
      5.633333333333349,
      2.1,
      5.6,
      7.1,
      5.3,
      3.7,
      5.7,
      3.5,
      0.6,
      1.9,
      1.1
    ]
  },
  "Ad Damm\u0101m, Ash Sharq\u012byah, Saudi Arabia": {
    "lats": [
      20.366767962526406
    ],
    "lons": [
      42.50221915849673
    ],
    "true_lat": 26.4282,
    "true_lon": 50.0997,
    "wiki": "https://en.wikipedia.org/wiki/Special:Search?search=Ad Damm\u0101m%2C+Saudi Arabia&go=Go&ns0=1",
    "mean_dist": 1026.8,
    "mean_lat": 20.366,
    "mean_lon": 42.502,
    "mean_time": 9.5,
    "std_dist": 0,
    "std_time": 0,
    "city": "Ad Damm\u0101m",
    "admin": "Ash Sharq\u012byah",
    "country": "Saudi Arabia",
    "iso2": "SA",
    "regions": [
      "Lima"
    ],
    "countries": [
      "Peru"
    ],
    "dists": [
      1026.842602249659
    ],
    "times": [
      9.533333333333335
    ]
  },
  "Al Kharj, Ar Riy\u0101\u1e11, Saudi Arabia": {
    "lats": [
      31.38296547837594,
      24.962,
      26.131,
      19.815,
      21.303,
      27.41
    ],
    "lons": [
      41.556749387254904,
      45.682,
      42.886,
      40.674,
      40.908,
      49.15
    ],
    "true_lat": 24.1556,
    "true_lon": 47.312,
    "wiki": "https://en.wikipedia.org/wiki/Special:Search?search=Al Kharj%2C+Saudi Arabia&go=Go&ns0=1",
    "mean_dist": 606.5,
    "mean_lat": 25.167,
    "mean_lon": 43.476,
    "mean_time": 6.1,
    "std_dist": 270,
    "std_time": 1.7,
    "city": "Al Kharj",
    "admin": "Ar Riy\u0101\u1e11",
    "country": "Saudi Arabia",
    "iso2": "SA",
    "regions": [
      "Lima",
      "England",
      "England",
      "England",
      "England",
      "Riyadh Region"
    ],
    "countries": [
      "Peru",
      "United Kingdom",
      "United Kingdom",
      "United Kingdom",
      "United Kingdom",
      "Saudi Arabia"
    ],
    "dists": [
      982.6750937126894,
      187.6,
      496.6,
      837.1,
      729.1,
      406
    ],
    "times": [
      9.666666666666668,
      6.2,
      4.3,
      6.1,
      5.1,
      5.3
    ]
  },
  "As Sulayyil, Ar Riy\u0101\u1e11, Saudi Arabia": {
    "lats": [
      24.219629905475497,
      25.25484482601112,
      22.728893079191412,
      24.238645351823923
    ],
    "lons": [
      44.558169934640524,
      44.90600952958749,
      44.77304942810458,
      47.246352926329074
    ],
    "true_lat": 20.4623,
    "true_lon": 45.5722,
    "wiki": "https://en.wikipedia.org/wiki/Special:Search?search=As Sulayyil%2C+Saudi Arabia&go=Go&ns0=1",
    "mean_dist": 421.7,
    "mean_lat": 24.11,
    "mean_lon": 45.37,
    "mean_time": 4,
    "std_dist": 98.6,
    "std_time": 1,
    "city": "As Sulayyil",
    "admin": "Ar Riy\u0101\u1e11",
    "country": "Saudi Arabia",
    "iso2": "SA",
    "regions": [
      "Quebec",
      "Hawalli",
      "Riyadh Region",
      "Medina Region"
    ],
    "countries": [
      "Canada",
      "Kuwait",
      "Saudi Arabia",
      "Saudi Arabia"
    ],
    "dists": [
      430.6092183602799,
      537.2566437535875,
      265.2288368702402,
      453.8188925247805
    ],
    "times": [
      4.5000000000000195,
      4.8000000000000185,
      4.766666666666685,
      2.266666666666694
    ]
  }
}